{
  "berkbubus": "XplaiNLP",
  "jct_sb": "JCT",
  "jjuliar": "INF-rsrs",
  "mrshu": "RAGthoven",
  "oseminck": "Lattice",
  "t_abbasi7": "YNWA_AZ",
  "sinaeskandari": "MINDS",
  "abdulmj1": "AI4PC",
  "stefanoprea": "FunnyBorg",
  "zhangxulong": "YNU-HPCC",
  "mdehouck": "Lattice_Dev",
  "clashing": "CUET_clashing",
  "tanlocn": "DANGNT@SGU",
  "ahoblitz": "BAHAHA",
  "soyliz30": "L52+-IIMAS-UNAM",
  "shenwutao": "ICT-NLP",
  "warda_yousaf": "SLPG_FJWU_Warda",
  "abaruah": "ABARUAH",
  "SLPG_FJWU_Insa": "SLPG_FJWU_Insa",
  "luttt": "TüLK",
  "arampageos": "DUTH",
  "jayicodes": "Edward Ajayi"
}
